xytext/__init__.py
xytext/api.py
xytext-1.0.6.dist-info/METADATA
xytext-1.0.6.dist-info/WHEEL
xytext-1.0.6.dist-info/top_level.txt
xytext-1.0.6.dist-info/RECORD
